wheel_compile/__init__.py
wheel_compile/audit.py
wheel_compile/cli.py
wheel_compile/compile.py
wheel_compile/compiler/__init__.py
wheel_compile/compiler/abc.py
wheel_compile/compiler/cython.py
wheel_compile/compiler/map.py
wheel_compile/compiler/native.py
wheel_compile/container.py
wheel_compile/py.typed
wheel_compile-0.4.0.dist-info/entry_points.txt
wheel_compile-0.4.0.dist-info/LICENSE.txt
wheel_compile-0.4.0.dist-info/WHEEL
wheel_compile-0.4.0.dist-info/METADATA
wheel_compile-0.4.0.dist-info/RECORD
