Metadata-Version: 2.1
Name: wheel-compile
Version: 0.4.0
Summary: Python wheel compilation to clean up source files from distro.
Home-page: https://bitbucket.org/p-app/wheel_compile
License: MIT
Author: Vladimir V. Pivovarov
Author-email: admin@p-app.ru
Maintainer: Vladimir V. Pivovarov
Maintainer-email: admin@p-app.ru
Requires-Python: >=3.8,<4.0
Classifier: Development Status :: 4 - Beta
Classifier: Intended Audience :: Developers
Classifier: License :: OSI Approved :: MIT License
Classifier: Programming Language :: Python :: 3
Classifier: Programming Language :: Python :: 3.10
Classifier: Programming Language :: Python :: 3.8
Classifier: Programming Language :: Python :: 3.9
Classifier: Topic :: Software Development :: Libraries :: Python Modules
Provides-Extra: audit
Provides-Extra: cython
Requires-Dist: Cython (>=0.29.32,<0.30.0); extra == "cython"
Requires-Dist: auditwheel (>=5.3.0,<5.4.0); extra == "audit"
Requires-Dist: setuptools (>=67.0.0,<68.0.0)
Requires-Dist: wheel (>=0.38.0,<0.39.0)
Project-URL: Repository, https://bitbucket.org/p-app/wheel_compile
